setup.py
lessrpc_stub/StubConstants.py
lessrpc_stub/__init__.py
lessrpc_stub/cache.py
lessrpc_stub/errors.py
lessrpc_stub/serializer.py
lessrpc_stub.egg-info/PKG-INFO
lessrpc_stub.egg-info/SOURCES.txt
lessrpc_stub.egg-info/dependency_links.txt
lessrpc_stub.egg-info/requires.txt
lessrpc_stub.egg-info/top_level.txt
lessrpc_stub/stubs/__init__.py
lessrpc_stub/stubs/base.py
lessrpc_stub/stubs/client.py
lessrpc_stub/stubs/server.py