Metadata-Version: 1.2
Name: lessrpc-stub
Version: 1.0.11
Summary: Less RPC stubs project
Home-page: https://github.com/LessRPC/lessrpc_stub_py2x/
Author: Salim Malakouti
Author-email: salim.malakouti@gmail.com
License: MIT
Download-URL: https://github.com/LessRPC/lessrpc_stub_py2x/archive/1.0.11.tar.gz
Keywords: python,serialization,deserialization,rpc,rmi,less rpc,client,server
Platform: UNKNOWN
Classifier: Programming Language :: Python :: 2.7
Requires-Python: ~=2.7
